cr_kyoushi/simulation/__init__.py
cr_kyoushi/simulation/__main__.py
cr_kyoushi/simulation/cli.py
cr_kyoushi/simulation/config.py
cr_kyoushi/simulation/errors.py
cr_kyoushi/simulation/logging.py
cr_kyoushi/simulation/model.py
cr_kyoushi/simulation/plugins.py
cr_kyoushi/simulation/sm.py
cr_kyoushi/simulation/states.py
cr_kyoushi/simulation/transitions.py
cr_kyoushi/simulation/util.py
kyoushi_simulation-0.3.10.dist-info/entry_points.txt
kyoushi_simulation-0.3.10.dist-info/LICENSE
kyoushi_simulation-0.3.10.dist-info/WHEEL
kyoushi_simulation-0.3.10.dist-info/METADATA
kyoushi_simulation-0.3.10.dist-info/RECORD
